trafiklab_sl-2.2.0.dist-info/licenses/LICENSE.txt
tsl/__init__.py
tsl/utils.py
tsl/clients/__init__.py
tsl/clients/common.py
tsl/clients/deviations.py
tsl/clients/journey.py
tsl/clients/stoplookup.py
tsl/clients/transport.py
tsl/helpers/__init__.py
tsl/helpers/cache.py
tsl/helpers/lines.py
tsl/helpers/search.py
tsl/helpers/stops.py
tsl/models/__init__.py
tsl/models/common.py
tsl/models/departures.py
tsl/models/deviations.py
tsl/models/journey.py
tsl/models/sites.py
tsl/models/stops.py
tsl/models/transport.py
tsl/tools/__init__.py
tsl/tools/journey.py
tsl/tools/stop_ids.py
trafiklab_sl-2.2.0.dist-info/METADATA
trafiklab_sl-2.2.0.dist-info/WHEEL
trafiklab_sl-2.2.0.dist-info/top_level.txt
trafiklab_sl-2.2.0.dist-info/RECORD
