Metadata-Version: 2.4
Name: trafiklab-sl
Version: 2.2.0
Summary: Storstockholms Lokaltrafik (SL) data via Trafiklab API
Author-email: Mikalai Kukhta <mikalai.kukhta@gmail.com>
License: Copyright (c) 2024 Mikalai Kukhta and individual contributors.
Project-URL: Repository, https://github.com/NecroKote/trafiklab-sl
Project-URL: Issues, https://github.com/NecroKote/trafiklab-sl/issues
Keywords: SL,Storstockholms Lokaltrafik,Trafiklab
Classifier: Development Status :: 3 - Alpha
Classifier: Intended Audience :: Developers
Classifier: License :: OSI Approved :: MIT License
Classifier: Programming Language :: Python :: 3
Classifier: Programming Language :: Python :: 3.11
Classifier: Programming Language :: Python :: 3.12
Classifier: Programming Language :: Python :: 3.13
Classifier: Topic :: Software Development :: Libraries
Requires-Python: >=3.11.0
License-File: LICENSE.txt
Requires-Dist: aiohttp
Provides-Extra: dev
Requires-Dist: wheel; extra == "dev"
Requires-Dist: build; extra == "dev"
Requires-Dist: twine; extra == "dev"
Requires-Dist: tox; extra == "dev"
Requires-Dist: isort; extra == "dev"
Requires-Dist: black; extra == "dev"
Requires-Dist: pre-commit; extra == "dev"
Provides-Extra: test
Requires-Dist: pytest==8.0.0; extra == "test"
Requires-Dist: pytest-asyncio==0.23.5; extra == "test"
Dynamic: license-file
